README.rst
setup.py
src/django_werewolf.egg-info/PKG-INFO
src/django_werewolf.egg-info/SOURCES.txt
src/django_werewolf.egg-info/dependency_links.txt
src/django_werewolf.egg-info/requires.txt
src/django_werewolf.egg-info/top_level.txt
src/werewolf/__init__.py
src/werewolf/admin.py
src/werewolf/base.py
src/werewolf/conf.py
src/werewolf/constants.py
src/werewolf/defaults.py
src/werewolf/helpers.py
src/werewolf/settings.py
src/werewolf/tests.py
src/werewolf/triggers.py
src/werewolf/utils.py
src/werewolf/management/__init__.py
src/werewolf/management/commands/__init__.py
src/werewolf/management/commands/syncww.py
src/werewolf/models/__init__.py
src/werewolf/models/fields.py
src/werewolf/models/managers.py