Metadata-Version: 1.1
Name: django-werewolf
Version: 0.4.2
Summary: Item publishing workflow for Django.
Home-page: https://github.com/barseghyanartur/django-werewolf
Author: Artur Barseghyan
Author-email: artur.barseghyan@gmail.com
License: GPL 2.0/LGPL 2.1
Keywords: workflow,publishing,django workflow
Platform: UNKNOWN
Classifier: Programming Language :: Python
Classifier: Programming Language :: Python :: 2.6
Classifier: Programming Language :: Python :: 2.7
Classifier: Programming Language :: Python :: 3
Classifier: Programming Language :: Python :: 3.3
Classifier: Environment :: Web Environment
Classifier: Framework :: Django
Classifier: Intended Audience :: Developers
Classifier: Operating System :: OS Independent
Classifier: Development Status :: 5 - Production/Stable
Classifier: License :: OSI Approved :: GNU General Public License v2 (GPLv2)
Classifier: License :: OSI Approved :: GNU Lesser General Public License v2 or later (LGPLv2+)
